mysql_grantparser/__init__.py
mysql_grantparser/__metadata__.py
mysql_grantparser/driver.py
mysql_grantparser/exporter.py
mysql_grantparser/parser.py
mysql_grantparser-1.0.5.dist-info/LICENSE
mysql_grantparser-1.0.5.dist-info/METADATA
mysql_grantparser-1.0.5.dist-info/WHEEL
mysql_grantparser-1.0.5.dist-info/top_level.txt
mysql_grantparser-1.0.5.dist-info/RECORD
