Metadata-Version: 2.1
Name: mysql-grantparser
Version: 1.0.5
Summary: parse MySQL SHOW GRANTS.
Home-page: https://github.com/hirose31/mysql-grantparser-python
Author: HIROSE Masaaki
Author-email: hirose31@gmail.com
License: MIT
Keywords: MySQL
Classifier: Development Status :: 5 - Production/Stable
Classifier: Intended Audience :: Developers
Classifier: License :: OSI Approved :: MIT License
Classifier: Programming Language :: Python :: 3.5
Classifier: Programming Language :: Python :: 3.6
Classifier: Programming Language :: Python :: 3.7
Classifier: Topic :: Database
Requires-Python: >=3.5
License-File: LICENSE
Requires-Dist: setuptools (>=30.3.0)
Requires-Dist: mysql-connector-python
Provides-Extra: dev
Requires-Dist: pytest (>=3) ; extra == 'dev'
Requires-Dist: coverage ; extra == 'dev'
Requires-Dist: tox ; extra == 'dev'
